wile/__init__.py
wile/argtypes.py
wile/cert.py
wile/lazyclient.py
wile/reg.py
wile/sftp_helper.py
wile-1.0.6.dist-info/LICENSE
wile-1.0.6.dist-info/METADATA
wile-1.0.6.dist-info/WHEEL
wile-1.0.6.dist-info/entry_points.txt
wile-1.0.6.dist-info/top_level.txt
wile-1.0.6.dist-info/RECORD
