Metadata-Version: 2.1
Name: wile
Version: 1.0.6
Summary: A stripped down Let's Encrypt (ACME) client
Home-page: https://github.com/costela/wile
Author: Leo Antunes
Author-email: leo@costela.net
License: GPLv3
Keywords: letsencrypt acme ssl
Platform: UNKNOWN
Classifier: Development Status :: 4 - Beta
Classifier: Environment :: Console
Classifier: License :: OSI Approved :: GNU General Public License v3 (GPLv3)
Classifier: Operating System :: POSIX :: Linux
Classifier: Programming Language :: Python
Classifier: Topic :: Internet :: Name Service (DNS)
Classifier: Topic :: Security :: Cryptography
Classifier: Topic :: Utilities
Requires-Dist: six
Requires-Dist: acme (!=0.22.0,>=0.21.0)
Requires-Dist: click (<7.0,>=6.0)
Requires-Dist: pyOpenSSL
Requires-Dist: cryptography
Requires-Dist: setuptools-scm
Requires-Dist: paramiko
Requires-Dist: josepy
